Metadata-Version: 2.1
Name: fast-web-admin
Version: 0.1.4
Summary: FastAPI Admin Framework
Home-page: https://gitee.com/buffaloboy/fast-admin
Author: buffalo
License: MIT
Keywords: fastapi,fastapi-admin
Platform: any
Classifier: Development Status :: 3 - Alpha
Classifier: License :: OSI Approved :: MIT License
Classifier: Operating System :: OS Independent
Classifier: Programming Language :: Python
Classifier: Programming Language :: Python :: 3
Classifier: Programming Language :: Python :: 3.8
Classifier: Programming Language :: Python :: Implementation :: CPython
Requires-Dist: fastapi
Requires-Dist: sqlalchemy
Requires-Dist: uvicorn
